README.md
setup.py
gptgladiator/ChatBot.py
gptgladiator/GPTModel.py
gptgladiator/Gladiator.py
gptgladiator/__init__.py
gptgladiator/mocks.py
gptgladiator/prompts.py
gptgladiator.egg-info/PKG-INFO
gptgladiator.egg-info/SOURCES.txt
gptgladiator.egg-info/dependency_links.txt
gptgladiator.egg-info/requires.txt
gptgladiator.egg-info/top_level.txt