Metadata-Version: 2.1
Name: gptgladiator
Version: 0.1.3
Summary: Generate multiple draft responses and then use a second model to judge the answers and pick a winner, which is then returned to the user.
Home-page: https://github.com/TheoremOne/gladiator/
Author: Will Jessup
Author-email: Will@theoremone.co
